ripiu/cmsplugin_filer_svg/__init__.py
ripiu/cmsplugin_filer_svg/apps.py
ripiu/cmsplugin_filer_svg/cms_plugins.py
ripiu/cmsplugin_filer_svg/models.py
ripiu/cmsplugin_filer_svg/locale/it/LC_MESSAGES/django.po
ripiu/cmsplugin_filer_svg/migrations/0001_initial.py
ripiu/cmsplugin_filer_svg/migrations/0002_filersvginlinepluginmodel.py
ripiu/cmsplugin_filer_svg/migrations/0003_auto_20180327_1242.py
ripiu/cmsplugin_filer_svg/migrations/0004_auto_20180327_1511.py
ripiu/cmsplugin_filer_svg/migrations/__init__.py
ripiu/cmsplugin_filer_svg/templates/ripiu/cmsplugin_filer_svg/inline.svg
ripiu/cmsplugin_filer_svg/templates/ripiu/cmsplugin_filer_svg/ref.html
ripiu.cmsplugin_filer_svg-0.2.2.dist-info/LICENSE.txt
ripiu.cmsplugin_filer_svg-0.2.2.dist-info/METADATA
ripiu.cmsplugin_filer_svg-0.2.2.dist-info/RECORD
ripiu.cmsplugin_filer_svg-0.2.2.dist-info/WHEEL
ripiu.cmsplugin_filer_svg-0.2.2.dist-info/top_level.txt
