Metadata-Version: 2.1
Name: ripiu.cmsplugin-filer-svg
Version: 0.2.2
Summary: Use SVG images in a Django-cms site
Home-page: https://github.com/ripiu/cmsplugin_filer_svg
Author: matteo vezzola
Author-email: matteo@studioripiu.it
License: BSD-new
Platform: UNKNOWN
Classifier: Development Status :: 3 - Alpha
Classifier: Framework :: Django
Classifier: Intended Audience :: Developers
Classifier: License :: OSI Approved :: BSD License
Classifier: Operating System :: OS Independent
Classifier: Programming Language :: Python
Classifier: Topic :: Internet :: WWW/HTTP :: Dynamic Content
Requires-Python: >=3.3
Requires-Dist: Django (>=1.8)
Requires-Dist: django-cms (>=3.1)
Requires-Dist: django-filer (>=1.2.4)
